strform/__init__.py
strform/brackets.py
strform/requirements.txt
strform/__pycache__/__init__.cpython-37.pyc
strform-0.0.1.dist-info/LICENSE.txt
strform-0.0.1.dist-info/METADATA
strform-0.0.1.dist-info/WHEEL
strform-0.0.1.dist-info/top_level.txt
strform-0.0.1.dist-info/RECORD
