Metadata-Version: 2.1
Name: strform
Version: 0.0.1
Summary: STR sequence compression and formatting
Home-page: https://github.com/alexyyl/STRform
Author: Alexander YY Liu
Author-email: yliu575@aucklanduni.ac.nz
License: UNKNOWN
Download-URL: https://github.com/alexyyl/STRform/releases/tag/v_0.0.1.tar.gz
Keywords: forensic STR,bracketed repeat formatting
Platform: UNKNOWN
Classifier: Development Status :: 1 - Planning
Classifier: Intended Audience :: Science/Research
Classifier: Topic :: Scientific/Engineering :: Bio-Informatics
Classifier: Programming Language :: Python :: 3.6
Requires-Python: >=3.6
